Basic Hardware Implementations/FullAdder.v
module FullAdder (
    input a,     // Input bit a
    input b,     // Input bit b
    input cin,   // Carry-in
    output sum,  // Sum output
    output cout  // Carry-out
);
    // The sum and carry-out logic
    assign sum = a ^ b ^ cin;
    assign cout = (a & b) | (b & cin)  | (cin & a) ;
endmodule

Basic Hardware Implementations/FullAdder_tb.v
`timescale 1ns / 1ns

module FullAdder_tb;

    // Declare inputs as reg type
    reg a;
    reg b;
    reg cin;

    // Declare outputs as wire type
    wire sum;
    wire cout;

    // Instantiate the FullAdder module
    FullAdder uut (
        .a(a), 
        .b(b), 
        .cin(cin), 
        .sum(sum), 
        .cout(cout)
    );

    initial begin
        // Set up the VCD (Value Change Dump) file for waveform viewing
        $dumpfile("fulladder_tb_output.vcd");
        $dumpvars(0, FullAdder_tb);
        
        // Initialize inputs
        a = 0; b = 0; cin = 0;
        #10; // Wait for 10 time units

        a = 0; b = 0; cin = 1;
        #10;

        a = 0; b = 1; cin = 0;
        #10;

        a = 0; b = 1; cin = 1;
        #10;

        a = 1; b = 0; cin = 0;
        #10;

        a = 1; b = 0; cin = 1;
        #10;

        a = 1; b = 1; cin = 0;
        #10;

        a = 1; b = 1; cin = 1;
        #10;

        // End the simulation
        $finish;
    end

endmodule

Basic Hardware Implementations/fulladder_tb_output.vcd
$date
	Fri Oct 18 12:07:00 2024
$end
$version
	Icarus Verilog
$end
$timescale
	1ns
$end
$scope module FullAdder_tb $end
$var wire 1 ! sum $end
$var wire 1 " cout $end
$var reg 1 # a $end
$var reg 1 $ b $end
$var reg 1 % cin $end
$scope module uut $end
$var wire 1 # a $end
$var wire 1 $ b $end
$var wire 1 % cin $end
$var wire 1 " cout $end
$var wire 1 ! sum $end
$upscope $end
$upscope $end
$enddefinitions $end
$comment Show the parameter values. $end
$dumpall
$end
#0
$dumpvars
0%
0$
0#
0"
0!
$end
#10
1!
1%
#20
0%
1$
#30
1"
0!
1%
#40
0"
1!
0%
0$
1#
#50
1"
0!
1%
#60
0%
1$
#70
1!
1%
