Basic Hardware Implementations/fullsubtractor.v
module FullSubtractor(
    input A, 
    input B, 
    input Bin,
    output D, 
    output Bout
);
assign D = A ^ B ^ Bin;
assign Bout = (~A & B) | (B & Bin) | (~A & Bin);
endmodule

Basic Hardware Implementations/fullsubtractor_tb.v
`timescale 1ns / 1ns

module FullSubtractor_tb;

    // Declare inputs as reg type
    reg A;
    reg B;
    reg Bin;

    // Declare outputs as wire type
    wire D;
    wire Bout;

    // Instantiate the FullSubtractor module
    FullSubtractor uut (
        .A(A), 
        .B(B), 
        .Bin(Bin), 
        .D(D), 
        .Bout(Bout)
    );

    initial begin
        // Set up the VCD (Value Change Dump) file for waveform viewing
        $dumpfile("fullsubtractor_tb_output.vcd");
        $dumpvars(0, FullSubtractor_tb);
        
        // Initialize inputs
        A = 0; B = 0; Bin = 0;
        #10; // Wait for 10 time units

        A = 0; B = 0; Bin = 1;
        #10;

        A = 0; B = 1; Bin = 0;
        #10;

        A = 0; B = 1; Bin = 1;
        #10;

        A = 1; B = 0; Bin = 0;
        #10;

        A = 1; B = 0; Bin = 1;
        #10;

        A = 1; B = 1; Bin = 0;
        #10;

        A = 1; B = 1; Bin = 1;
        #10;

        // End the simulation
        $finish;
    end

endmodule

Basic Hardware Implementations/fullsubtractor_tb_output.vcd
$date
	Fri Oct 18 12:18:31 2024
$end
$version
	Icarus Verilog
$end
$timescale
	1ns
$end
$scope module FullSubtractor_tb $end
$var wire 1 ! D $end
$var wire 1 " Bout $end
$var reg 1 # A $end
$var reg 1 $ B $end
$var reg 1 % Bin $end
$scope module uut $end
$var wire 1 # A $end
$var wire 1 $ B $end
$var wire 1 % Bin $end
$var wire 1 " Bout $end
$var wire 1 ! D $end
$upscope $end
$upscope $end
$enddefinitions $end
$comment Show the parameter values. $end
$dumpall
$end
#0
$dumpvars
0%
0$
0#
0"
0!
$end
#10
1"
1!
1%
#20
0%
1$
#30
0!
1%
#40
0"
1!
0%
0$
1#
#50
0!
1%
#60
0%
1$
#70
1"
1!
1%
